openagua_engine/__init__.py
openagua_engine/celery_app.py
openagua_engine/celeryconfig.py
openagua_engine/constants.py
openagua_engine/engine.py
openagua_engine/utils.py
openagua_engine/publishers/__init__.py
openagua_engine/publishers/ably.py
openagua_engine/publishers/pubnub.py
openagua_engine/publishers/rabbitmq.py
openagua_engine/publishers/redis.py
openagua_engine/subscribers/__init__.py
openagua_engine/subscribers/pubnub.py
openagua_engine/tests/__init__.py
openagua_engine/tests/test_app.py
openagua_engine-0.2.18.dist-info/LICENSE
openagua_engine-0.2.18.dist-info/METADATA
openagua_engine-0.2.18.dist-info/WHEEL
openagua_engine-0.2.18.dist-info/top_level.txt
openagua_engine-0.2.18.dist-info/RECORD
