Metadata-Version: 2.1
Name: openagua-engine
Version: 0.2.18
Summary: Tools to connect a model engine to OpenAgua
Home-page: https://github.com/openagua/openagua-engine
Author: David Rheinheimer
Author-email: david.rheinheimer@tec.mx
License: MIT
Platform: UNKNOWN
Classifier: Programming Language :: Python :: 3
Classifier: License :: OSI Approved :: MIT License
Classifier: Operating System :: OS Independent
Requires-Python: >=3.6
License-File: LICENSE
Requires-Dist: celery
Requires-Dist: pubnub
Requires-Dist: requests
Requires-Dist: openagua-client
Requires-Dist: loguru
